steamclient/__init__.py
steamclient-1.2.dist-info/METADATA
steamclient-1.2.dist-info/WHEEL
steamclient-1.2.dist-info/top_level.txt
steamclient-1.2.dist-info/RECORD
