Metadata-Version: 2.1
Name: steamclient
Version: 1.2
Summary: Steam Client API
Home-page: https://gitlab.com/avalonparton/steam-client
Author: Avalon Parton
Author-email: avalonlee@gmail.com
License: MIT
Platform: UNKNOWN
Requires-Dist: requests
